xmind2testlink/__init__.py
xmind2testlink/datatype.py
xmind2testlink/main.py
xmind2testlink/sharedparser.py
xmind2testlink/testlink_parser.py
xmind2testlink/xmind_parser.py
xmind2testlink-2.0.9.dist-info/LICENSE
xmind2testlink-2.0.9.dist-info/METADATA
xmind2testlink-2.0.9.dist-info/WHEEL
xmind2testlink-2.0.9.dist-info/entry_points.txt
xmind2testlink-2.0.9.dist-info/top_level.txt
xmind2testlink-2.0.9.dist-info/RECORD
