Metadata-Version: 2.1
Name: xmind2testlink
Version: 2.0.9
Summary: Convert xmind to TestLink xml
Home-page: https://github.com/tobyqin/xmind2testlink
Author: Toby Qin
Author-email: toby.qin@live.com
License: UNKNOWN
Keywords: xmind testlink import converter testing testcase
Platform: UNKNOWN
Classifier: License :: OSI Approved :: MIT License
Classifier: Topic :: Software Development
Classifier: Topic :: Utilities
Classifier: Operating System :: Microsoft :: Windows
Classifier: Operating System :: MacOS :: MacOS X
Classifier: Programming Language :: Python :: 2.7
Classifier: Programming Language :: Python :: 3.5
Classifier: Programming Language :: Python :: 3.6
Classifier: Programming Language :: Python :: 3.7
Classifier: Programming Language :: Python :: 3.8
Requires-Dist: xmindparser
